<?xml version="1.0" encoding="UTF-8"?><record_update>
    <sys_choice action="INSERT_OR_UPDATE" field="state" table="x_601959_loaner_re_loaner_request" version="3">
        <sys_choice_set action="INSERT_OR_UPDATE">
            <element>state</element>
            <name>x_601959_loaner_re_loaner_request</name>
            <sys_class_name>sys_choice_set</sys_class_name>
            <sys_created_by>admin</sys_created_by>
            <sys_created_on>2021-05-01 06:46:59</sys_created_on>
            <sys_id>54a333de1b376010a46ea9f9bc4bcb25</sys_id>
            <sys_mod_count>0</sys_mod_count>
            <sys_name>state</sys_name>
            <sys_package display_value="loaner request" source="x_601959_loaner_re">2aea999e1bbf2010a46ea9f9bc4bcbea</sys_package>
            <sys_policy/>
            <sys_scope display_value="loaner request">2aea999e1bbf2010a46ea9f9bc4bcbea</sys_scope>
            <sys_update_name>sys_choice_x_601959_loaner_re_loaner_request_state</sys_update_name>
            <sys_updated_by>admin</sys_updated_by>
            <sys_updated_on>2021-05-01 06:46:59</sys_updated_on>
        </sys_choice_set>
        <sys_choice action="INSERT_OR_UPDATE">
            <dependent_value/>
            <element>state</element>
            <hint/>
            <inactive>false</inactive>
            <label>Requested</label>
            <language>en</language>
            <name>x_601959_loaner_re_loaner_request</name>
            <sequence>0</sequence>
            <sys_created_by>admin</sys_created_by>
            <sys_created_on>2021-05-01 06:46:59</sys_created_on>
            <sys_domain>global</sys_domain>
            <sys_domain_path>/</sys_domain_path>
            <sys_id>1ca333de1b376010a46ea9f9bc4bcb24</sys_id>
            <sys_mod_count>0</sys_mod_count>
            <sys_updated_by>admin</sys_updated_by>
            <sys_updated_on>2021-05-01 06:46:59</sys_updated_on>
            <value>13</value>
        </sys_choice>
        <sys_choice action="INSERT_OR_UPDATE">
            <dependent_value/>
            <element>state</element>
            <hint/>
            <inactive>false</inactive>
            <label>Reserve</label>
            <language>en</language>
            <name>x_601959_loaner_re_loaner_request</name>
            <sequence>1</sequence>
            <sys_created_by>admin</sys_created_by>
            <sys_created_on>2021-05-01 06:46:59</sys_created_on>
            <sys_domain>global</sys_domain>
            <sys_domain_path>/</sys_domain_path>
            <sys_id>dca333de1b376010a46ea9f9bc4bcb27</sys_id>
            <sys_mod_count>0</sys_mod_count>
            <sys_updated_by>admin</sys_updated_by>
            <sys_updated_on>2021-05-01 06:46:59</sys_updated_on>
            <value>14</value>
        </sys_choice>
        <sys_choice action="INSERT_OR_UPDATE">
            <dependent_value/>
            <element>state</element>
            <hint/>
            <inactive>false</inactive>
            <label>Deployment Prep</label>
            <language>en</language>
            <name>x_601959_loaner_re_loaner_request</name>
            <sequence>2</sequence>
            <sys_created_by>admin</sys_created_by>
            <sys_created_on>2021-05-01 06:46:59</sys_created_on>
            <sys_domain>global</sys_domain>
            <sys_domain_path>/</sys_domain_path>
            <sys_id>9ca333de1b376010a46ea9f9bc4bcb29</sys_id>
            <sys_mod_count>0</sys_mod_count>
            <sys_updated_by>admin</sys_updated_by>
            <sys_updated_on>2021-05-01 06:46:59</sys_updated_on>
            <value>15</value>
        </sys_choice>
        <sys_choice action="INSERT_OR_UPDATE">
            <dependent_value/>
            <element>state</element>
            <hint/>
            <inactive>false</inactive>
            <label>Ready for checkup</label>
            <language>en</language>
            <name>x_601959_loaner_re_loaner_request</name>
            <sequence>3</sequence>
            <sys_created_by>admin</sys_created_by>
            <sys_created_on>2021-05-01 06:46:59</sys_created_on>
            <sys_domain>global</sys_domain>
            <sys_domain_path>/</sys_domain_path>
            <sys_id>5ca333de1b376010a46ea9f9bc4bcb2b</sys_id>
            <sys_mod_count>0</sys_mod_count>
            <sys_updated_by>admin</sys_updated_by>
            <sys_updated_on>2021-05-01 06:46:59</sys_updated_on>
            <value>16</value>
        </sys_choice>
        <sys_choice action="INSERT_OR_UPDATE">
            <dependent_value/>
            <element>state</element>
            <hint/>
            <inactive>false</inactive>
            <label>Checked out</label>
            <language>en</language>
            <name>x_601959_loaner_re_loaner_request</name>
            <sequence>4</sequence>
            <sys_created_by>admin</sys_created_by>
            <sys_created_on>2021-05-01 06:46:59</sys_created_on>
            <sys_domain>global</sys_domain>
            <sys_domain_path>/</sys_domain_path>
            <sys_id>1ca333de1b376010a46ea9f9bc4bcb2d</sys_id>
            <sys_mod_count>0</sys_mod_count>
            <sys_updated_by>admin</sys_updated_by>
            <sys_updated_on>2021-05-01 06:46:59</sys_updated_on>
            <value>17</value>
        </sys_choice>
        <sys_choice action="INSERT_OR_UPDATE">
            <dependent_value/>
            <element>state</element>
            <hint/>
            <inactive>false</inactive>
            <label>post deployment</label>
            <language>en</language>
            <name>x_601959_loaner_re_loaner_request</name>
            <sequence>5</sequence>
            <sys_created_by>admin</sys_created_by>
            <sys_created_on>2021-05-01 06:46:59</sys_created_on>
            <sys_domain>global</sys_domain>
            <sys_domain_path>/</sys_domain_path>
            <sys_id>d8a333de1b376010a46ea9f9bc4bcb2f</sys_id>
            <sys_mod_count>0</sys_mod_count>
            <sys_updated_by>admin</sys_updated_by>
            <sys_updated_on>2021-05-01 06:46:59</sys_updated_on>
            <value>18</value>
        </sys_choice>
        <sys_choice action="INSERT_OR_UPDATE">
            <dependent_value/>
            <element>state</element>
            <hint/>
            <inactive>false</inactive>
            <label>closed complete</label>
            <language>en</language>
            <name>x_601959_loaner_re_loaner_request</name>
            <sequence>6</sequence>
            <sys_created_by>admin</sys_created_by>
            <sys_created_on>2021-05-01 06:46:59</sys_created_on>
            <sys_domain>global</sys_domain>
            <sys_domain_path>/</sys_domain_path>
            <sys_id>98a333de1b376010a46ea9f9bc4bcb31</sys_id>
            <sys_mod_count>0</sys_mod_count>
            <sys_updated_by>admin</sys_updated_by>
            <sys_updated_on>2021-05-01 06:46:59</sys_updated_on>
            <value>3</value>
        </sys_choice>
    </sys_choice>
</record_update>
